[
null,
{"id":1,"expanded":false,"name":"Test Scripts","order":1,"parentId":0,"scrollX":648,"scrollY":366},
{"id":2,"expanded":false,"name":"Bosque 12-3","order":2,"parentId":0,"scrollX":1488,"scrollY":1760.5714285714284},
{"id":3,"expanded":true,"name":"Mapamundo","order":3,"parentId":0,"scrollX":648,"scrollY":366},
{"id":4,"expanded":true,"name":"MAP004","order":8,"parentId":0,"scrollX":720,"scrollY":406.6666666666667},
{"id":5,"expanded":false,"name":"Megatropolis 13-1","order":6,"parentId":3,"scrollX":1823.9999999999998,"scrollY":1292.5714285714284},
{"id":6,"expanded":false,"name":"Megatropolis 13-2","order":7,"parentId":3,"scrollX":2156,"scrollY":1202},
{"id":7,"expanded":false,"name":"Megatropolis 12-2","order":4,"parentId":3,"scrollX":796,"scrollY":1961.3333333333333},
{"id":8,"expanded":false,"name":"Megatropolis 12-1","order":5,"parentId":3,"scrollX":816,"scrollY":1008},
{"id":9,"expanded":false,"name":"Bosque 11-3","order":9,"parentId":0,"scrollX":1568,"scrollY":624},
{"id":10,"expanded":false,"name":"Bosque 10-3","order":10,"parentId":0,"scrollX":1596,"scrollY":969.3333333333334},
{"id":11,"expanded":false,"name":"Ciudad Fantasma 3-7","order":11,"parentId":0,"scrollX":1690.6666666666667,"scrollY":956},
{"id":12,"expanded":false,"name":"Bosque 11-2","order":12,"parentId":0,"scrollX":1584,"scrollY":1776},
{"id":13,"expanded":false,"name":"Llanura 13-3","order":13,"parentId":0,"scrollX":1488,"scrollY":612},
{"id":14,"expanded":false,"name":"Bosque 11-1","order":14,"parentId":0,"scrollX":1568.3999999999999,"scrollY":1760.3999999999999}
]